README.rst
setup.py
django_render_partial/__init__.py
django_render_partial.egg-info/PKG-INFO
django_render_partial.egg-info/SOURCES.txt
django_render_partial.egg-info/dependency_links.txt
django_render_partial.egg-info/top_level.txt
django_render_partial/templatetags/__init__.py
django_render_partial/templatetags/render_partial.py