Metadata-Version: 1.1
Name: django-render-partial
Version: 0.1
Summary: Django render_partial tag allows inserting rendered views into templates
Home-page: https://github.com/utapyngo/django-render-partial
Author: utapyngo
Author-email: ut@pyngo.tom.ru
License: UNKNOWN
Keywords: django,render,partial,view,template,tag
Platform: UNKNOWN
Classifier: Development Status :: 3 - Alpha
Classifier: Operating System :: OS Independent
Classifier: Intended Audience :: Developers
Classifier: License :: OSI Approved :: BSD License
Classifier: Programming Language :: Python
Classifier: Programming Language :: Python :: 2
Classifier: Programming Language :: Python :: 2.7
Classifier: Programming Language :: Python :: 3
Classifier: Programming Language :: Python :: 3.4
Classifier: Topic :: Software Development :: Libraries
Classifier: Topic :: Utilities
Classifier: Environment :: Web Environment
Classifier: Framework :: Django
